LICENSE
MANIFEST.in
README.rst
setup.py
bee_django_user/__init__.py
bee_django_user/admin.py
bee_django_user/apps.py
bee_django_user/decorators.py
bee_django_user/dt.py
bee_django_user/exports.py
bee_django_user/forms.py
bee_django_user/middleware.py
bee_django_user/models.py
bee_django_user/signals.py
bee_django_user/tests.py
bee_django_user/urls.py
bee_django_user/utils.py
bee_django_user/validators.py
bee_django_user/views.py
bee_django_user/wxapp.py
bee_django_user/wxapp_urls.py
bee_django_user.egg-info/PKG-INFO
bee_django_user.egg-info/SOURCES.txt
bee_django_user.egg-info/dependency_links.txt
bee_django_user.egg-info/top_level.txt
bee_django_user/management/__init__.py
bee_django_user/management/__init__.pyc
bee_django_user/management/commands/__init__.py
bee_django_user/management/commands/__init__.pyc
bee_django_user/management/commands/create_group.py
bee_django_user/management/commands/create_superuser.py
bee_django_user/management/commands/create_superuser.pyc
bee_django_user/management/commands/set_group_perms.py
bee_django_user/management/commands/set_group_perms.pyc
bee_django_user/migrations/0001_initial.py
bee_django_user/migrations/0001_initial.pyc
bee_django_user/migrations/0002_auto_20180516_1834.py
bee_django_user/migrations/0002_auto_20180516_1834.pyc
bee_django_user/migrations/0003_auto_20180517_1641.py
bee_django_user/migrations/0003_auto_20180517_1641.pyc
bee_django_user/migrations/0004_auto_20181016_1500.py
bee_django_user/migrations/0004_auto_20181016_1500.pyc
bee_django_user/migrations/0005_auto_20181016_1619.py
bee_django_user/migrations/0005_auto_20181016_1619.pyc
bee_django_user/migrations/0006_userleaverecord.py
bee_django_user/migrations/0006_userleaverecord.pyc
bee_django_user/migrations/0007_auto_20181026_1751.py
bee_django_user/migrations/0007_auto_20181026_1751.pyc
bee_django_user/migrations/0008_auto_20181030_1316.py
bee_django_user/migrations/0008_auto_20181030_1316.pyc
bee_django_user/migrations/0009_userleavestatus.py
bee_django_user/migrations/0009_userleavestatus.pyc
bee_django_user/migrations/0010_auto_20181030_1459.py
bee_django_user/migrations/0010_auto_20181030_1459.pyc
